{"cameraMode":{"drawMode":0,"name":"Shaded","section":"Shading Mode"},"sceneLighting":true,"audioPlay":false,"sceneViewState":{"m_AlwaysRefresh":false,"showFog":true,"showSkybox":true,"showFlares":true,"showImageEffects":true,"showParticleSystems":true,"showVisualEffectGraphs":true,"m_FxEnabled":true},"in2DMode":false,"pivot":{"x":83.28385925292969,"y":8.063175201416016,"z":79.52059936523438},"rotation":{"x":0.22483451664447785,"y":-0.11195611953735352,"z":0.026022007688879968,"w":0.9676132202148438},"size":13.108962059020996,"orthographic":false}